warML/__init__.py
warML/sklearn/__init__.py
warML/sklearn/utils.py
warML-0.1.1.dist-info/LICENSE
warML-0.1.1.dist-info/METADATA
warML-0.1.1.dist-info/WHEEL
warML-0.1.1.dist-info/top_level.txt
warML-0.1.1.dist-info/RECORD
