Metadata-Version: 2.1
Name: warML
Version: 0.1.1
Summary: Utils to speed up ML iterations
Home-page: https://github.com/AlexandreRozier/fastML
Author: Alexandre Rozier
Author-email: alexandre.rozier@lilo.org
License: UNKNOWN
Platform: UNKNOWN
Classifier: Programming Language :: Python :: 3
Classifier: License :: OSI Approved :: MIT License
Classifier: Operating System :: OS Independent
Requires-Python: >=3.6
License-File: LICENSE
